risonia_theme/404.html
risonia_theme/__init__.py
risonia_theme/base.html
risonia_theme/main.html
risonia_theme/mkdocs_theme.yml
risonia_theme/css/theme.css
risonia_theme/css/w3-theme-dark.css
risonia_theme/css/w3-theme-light.css
risonia_theme/css/w3-theme.css
risonia_theme/css/w3.css
risonia_theme/img/favicon.ico
risonia_theme/js/theme.js
risonia_theme/plugins/__init__.py
risonia_theme/plugins/classes/__init__.py
risonia_theme/plugins/classes/plugin.py
risonia_theme/plugins/color/__init__.py
risonia_theme/plugins/color/plugin.py
mkdocs_risonia_theme-0.1.13.dist-info/LICENSE
mkdocs_risonia_theme-0.1.13.dist-info/METADATA
mkdocs_risonia_theme-0.1.13.dist-info/WHEEL
mkdocs_risonia_theme-0.1.13.dist-info/entry_points.txt
mkdocs_risonia_theme-0.1.13.dist-info/top_level.txt
mkdocs_risonia_theme-0.1.13.dist-info/RECORD
