Metadata-Version: 2.1
Name: mkdocs-risonia-theme
Version: 0.1.13
Summary: A simple theme for MkDocs using using the w3.css framework and configurable color schemes
Home-page: https://unverbuggt.github.io/mkdocs-risonia-theme/
Author: René Rüthlein
License: MIT
Keywords: mkdocs theme python markdown
Requires-Python: >=3.5
License-File: LICENSE
Requires-Dist: mkdocs
Requires-Dist: beautifulsoup4
